filepaths.py
bslint/__init__.py
bslint/__main__.py
bslint/bslint.py
bslint/constants.py
bslint/interface_handler.py
bslint/config/default-config.json
bslint/config/personal-words-list.txt
bslint/lexer/__init__.py
bslint/lexer/commands.py
bslint/lexer/lexer.py
bslint/lexer/regexs.py
bslint/lexer/token.py
bslint/lexer/words_dictionary.py
bslint/lexer/handlers/__init__.py
bslint/lexer/handlers/match_handler.py
bslint/lexer/handlers/regex_handler.py
bslint/lexer/handlers/styling_handler.py
bslint/messages/__init__.py
bslint/messages/builder.py
bslint/messages/error_constants.py
bslint/messages/handler.py
bslint/messages/print_constants.py
bslint/parser/__init__.py
bslint/parser/parser.py
bslint/parser/program_reduction_rules.py
bslint/parser/rule_builder.py
bslint/parser/statement_reduction_rules.py
bslint/utilities/__init__.py
bslint/utilities/config_loader.py
bslint/utilities/custom_exceptions.py
bslint/utilities/spinner.py
bslint-1.0.2.dist-info/DESCRIPTION.rst
bslint-1.0.2.dist-info/METADATA
bslint-1.0.2.dist-info/RECORD
bslint-1.0.2.dist-info/WHEEL
bslint-1.0.2.dist-info/entry_points.txt
bslint-1.0.2.dist-info/metadata.json
bslint-1.0.2.dist-info/top_level.txt
