Metadata-Version: 2.0
Name: bslint
Version: 1.0.2
Summary: A linter tool for the BrightScript language.
Home-page: https://github.com/sky-uk/bslint
Author: BSLint
Author-email: zachary.robinson@sky.uk
License: UNKNOWN
Platform: UNKNOWN
Requires-Dist: pyenchant (==1.6.8)
